last_air_bender/__init__.py
last_air_bender/setup.py
last_air_bender-0.0.1.dist-info/METADATA
last_air_bender-0.0.1.dist-info/WHEEL
last_air_bender-0.0.1.dist-info/top_level.txt
last_air_bender-0.0.1.dist-info/RECORD
